notouchie/__main__.py
notouchie/main.py
notouchie-0.1.0.dist-info/METADATA
notouchie-0.1.0.dist-info/WHEEL
notouchie-0.1.0.dist-info/entry_points.txt
notouchie-0.1.0.dist-info/RECORD
